CHANGELOG.txt
LICENSE.txt
MANIFEST.in
README.md
requirements.txt
setup.py
tobemodified.txt
stocksdata/__init__.py
stocksdata/stocksdata.py
stocksdata.egg-info/PKG-INFO
stocksdata.egg-info/SOURCES.txt
stocksdata.egg-info/dependency_links.txt
stocksdata.egg-info/requires.txt
stocksdata.egg-info/top_level.txt