Metadata-Version: 1.1
Name: stocksdata
Version: 1.0.2
Summary: Package of download bhavcopy data from nse website
Home-page: https://github.com/KiranNanduri/StockCode
Author: kiran nanduri
Author-email: kirannanduri@outlook.com
License: MIT
Keywords: nse
Platform: UNKNOWN
Classifier: Development Status :: 5 - Production/Stable
Classifier: Intended Audience :: Science/Research
Classifier: Operating System :: Microsoft :: Windows :: Windows 10
Classifier: Operating System :: POSIX :: Linux
Classifier: License :: OSI Approved :: MIT License
Classifier: Programming Language :: Python :: 3
